lisaconstants/__init__.py
lisaconstants/__main__.py
lisaconstants/_constants.py
lisaconstants/_error.py
lisaconstants/compat/__init__.py
lisaconstants/compat/astropy.py
lisaconstants/headers.py
lisaconstants/indexing.py
lisaconstants/py.typed
lisaconstants/templates/c.txt
lisaconstants/templates/cpp.txt
lisaconstants-2.0.2.dist-info/METADATA
lisaconstants-2.0.2.dist-info/WHEEL
lisaconstants-2.0.2.dist-info/licenses/LICENSE
lisaconstants-2.0.2.dist-info/RECORD
