Metadata-Version: 2.4
Name: lisaconstants
Version: 2.0.2
Summary: Provides values sanctioned by the LISA Science Ground Segment (SGS) for physical constants and mission parameters
License: BSD 3-Clause
License-File: LICENSE
Keywords: LISA,constants,parameters
Author: Jean-Baptiste Bayle
Author-email: j2b.bayle@gmail.com
Maintainer: Jean-Baptiste Bayle
Maintainer-email: j2b.bayle@gmail.com
Requires-Python: >=3.11,<4.0
Classifier: Intended Audience :: Science/Research
Classifier: Topic :: Scientific/Engineering :: Astronomy
Classifier: Topic :: Scientific/Engineering :: Physics
Requires-Dist: jinja2 (>=3.1.4)
Requires-Dist: numpy (>=2.1.2)
Project-URL: Documentation, https://lisa-sgs.io.esa.int/commons/lisa-constants
Project-URL: Download, https://gitlab.esa.int/lisa-sgs/commons/lisa-constants/-/releases
Project-URL: Issue Tracker, https://gitlab.esa.int/lisa-sgs/commons/lisa-constants/-/issues
Project-URL: Repository, https://gitlab.esa.int/lisa-sgs/commons/lisa-constants
